aws_lambda_rest_api
